{
  "timestamp": "2025-10-13T16:11:01.051Z",
  "searchQuery": "Ankit Mathur Senior Data Analyst Google",
  "totalResults": 1,
  "profiles": [
    {
      "index": 1,
      "name": ".Ankit M.",
      "headline": "Data Analyst| SQL | Python | Pandas | Tableau | Machine Learning | Deep Learning | Passionate Data Professional 📊 | Transforming Raw Data into Actionable Insights | Open to Work | Immediate Joiner |",
      "location": "India",
      "currentCompany": "Google",
      "currentPosition": "N/A",
      "linkedinUrl": "https://www.linkedin.com/in/ankit-m-8451b6115",
      "connectionsCount": 5074,
      "skillsCount": 72,
      "experienceCount": 3,
      "educationCount": 3
    }
  ],
  "originalFile": "harvestapi_Ankit_Mathur_Senior_Data_Analyst_Google_2025-10-13T16-11-01-051Z.json"
}