{
  "timestamp": "2025-10-09T07:29:31.154Z",
  "searchQuery": "Sahil Yadav Project Engineer Wipro",
  "totalResults": 1,
  "profiles": [
    {
      "index": 1,
      "name": "Sahil Yadav",
      "headline": "Project Engineer @ Wipro | Developing Engaging Web Interfaces",
      "location": "Mahendragarh, Haryana, India",
      "currentCompany": "Wipro",
      "currentPosition": "N/A",
      "linkedinUrl": "https://www.linkedin.com/in/sahil-yadav-3baba7230",
      "connectionsCount": 132,
      "skillsCount": 19,
      "experienceCount": 1,
      "educationCount": 4
    }
  ],
  "originalFile": "harvestapi_Sahil_Yadav_Project_Engineer_Wipro_2025-10-09T07-29-31-154Z.json"
}